Metadata-Version: 2.1
Name: vinorm_mac
Version: 3.0
Summary: Python package for text normalization, use for frontend of Text-to-speech Reseach
Home-page: https://github.com/v-nhandt21/Vinorm/tree/vinorm_mac
Author: Flower_On_Stone
Author-email: thuanbn03@gmail.com
License: AILAB
Classifier: Development Status :: 4 - Beta
Classifier: License :: Free for non-commercial use
Classifier: Natural Language :: Vietnamese
Classifier: Operating System :: MacOS :: MacOS X
Classifier: Programming Language :: C++
Classifier: Programming Language :: Python :: 3.6
Classifier: Topic :: Scientific/Engineering :: Artificial Intelligence
License-File: LICENSE
